{
	"include": [
		"Enum.json"
	],
	"struct": [
		{
			"name": "Vector2",
			"data": [
				{
					"type": "float",
					"name": "x"
				},
				{
					"type": "float",
					"name": "y"
				}
			]
		},
		{
			"name": "Vector3",
			"data": [
				{
					"type": "float",
					"name": "x"
				},
				{
					"type": "float",
					"name": "y"
				},
				{
					"type": "float",
					"name": "z"
				}
			]
		},
		{
			"name": "ObjectInfo",
			"data": [
				{
					"type": "uint64",
					"name": "objectId"
				},
				{
					"type": "Vector2",
					"name": "position"
				},
				{
					"type": "EObjectType",
					"name": "type"
				},
				{
					"type": "string",
					"name": "name"
				},
				{
					"type": "uint32",
					"name": "remainHp"
				}
			]
		},
		{
			"name": "DamageInfo",
			"data": [
				{
					"type": "uint64",
					"name": "objectId"
				},
				{
					"type": "uint32",
					"name": "damage"
				}
			]
		},
		{
			"name": "ItemInfo",
			"data": [
				{
					"type": "EItemType",
					"name": "type"
				},
				{
					"type": "uint16",
					"name": "amount"
				}
			]
		}
	]
}